README.md
setup.cfg
setup.py
loki_handler/__init__.py
loki_handler/cache.py
loki_handler/const.py
loki_handler/emitter.py
loki_handler/handlers.py
loki_handler.egg-info/PKG-INFO
loki_handler.egg-info/SOURCES.txt
loki_handler.egg-info/dependency_links.txt
loki_handler.egg-info/requires.txt
loki_handler.egg-info/top_level.txt