Metadata-Version: 2.1
Name: loki-handler
Version: 0.1.1
Summary: Python logging handler for Grafana Loki.
Home-page: https://github.com/cuerty/loki-handler
Author: Angel Freire
Author-email: cuerty@gmail.com
License: MIT
Platform: UNKNOWN
Classifier: Development Status :: 4 - Beta
Classifier: Intended Audience :: Developers
Classifier: License :: OSI Approved :: MIT License
Classifier: Operating System :: OS Independent
Classifier: Programming Language :: Python
Classifier: Programming Language :: Python :: 2
Classifier: Programming Language :: Python :: 2.7
Classifier: Topic :: Software Development :: Libraries :: Python Modules
Classifier: Topic :: System :: Logging
Classifier: Topic :: Internet :: WWW/HTTP
Requires-Python: >=2.7
